{
  "type":"solarforge:infusing",
  "input1": {
    "item": "solarforge:small_solar_reactor"
  },
  "input2": {
    "item": "solarforge:algadium_ingot"
  },
  "input3": {
    "item": "solarforge:solar_rune_ultima"
  },
  "input4": {
    "item": "solarforge:algadium_ingot"
  },
  "input5": {
    "item": "solarforge:solar_rune_ultima"
  },
  "input6": {
    "item": "solarforge:algadium_ingot"
  },
  "input7": {
    "item": "minecraft:obsidian"
  },
  "input8": {
    "item": "solarforge:algadium_ingot"
  },
  "input9": {
    "item": "minecraft:obsidian"
  },
  "result": {
    "item": "solarforge:explosion_blocker"
  },
  "time": 1000,
  "fragment": "explosion_blocker"
}